layer_enforcer/__init__.py
layer_enforcer/cli.py
layer_enforcer/grimp.py
layer_enforcer/impl.py
layer_enforcer/interfaces.py
layer_enforcer/py.typed
layer_enforcer/utils.py
layer_enforcer/config/__init__.py
layer_enforcer/config/args.py
layer_enforcer/config/interfaces.py
layer_enforcer/config/layers.py
layer_enforcer/config/multiple.py
layer_enforcer/config/pyproject.py
layer_enforcer/config/testing.py
layer_enforcer-0.2.0.dist-info/LICENSE
layer_enforcer-0.2.0.dist-info/METADATA
layer_enforcer-0.2.0.dist-info/WHEEL
layer_enforcer-0.2.0.dist-info/entry_points.txt
layer_enforcer-0.2.0.dist-info/top_level.txt
layer_enforcer-0.2.0.dist-info/RECORD
