Metadata-Version: 2.1
Name: layer-enforcer
Version: 0.2.0
Summary: Relaxed layer architecture linter based on the import graph.
Home-page: https://github.com/ZipFile/layer-enforcer
Author: Anatolii Aniskovych
Author-email: lin.aaa.lin@gmail.com
License: BSD 2-Clause License
Keywords: clean architecture,dependency rule
Classifier: Development Status :: 4 - Beta
Classifier: Intended Audience :: Developers
Classifier: License :: OSI Approved :: BSD License
Classifier: Programming Language :: Python :: 3
Classifier: Programming Language :: Python :: 3.8
Classifier: Programming Language :: Python :: 3.9
Classifier: Programming Language :: Python :: 3.10
Classifier: Topic :: Utilities
License-File: LICENSE
Requires-Dist: grimp (>=1.3)
Requires-Dist: pyyaml (>=5.1.0)
Requires-Dist: tomli (>=1.0.0) ; python_version < "3.11"
Provides-Extra: lint
Requires-Dist: black ; extra == 'lint'
Requires-Dist: flake8 ; extra == 'lint'
Requires-Dist: flake8-print ; extra == 'lint'
Requires-Dist: isort ; extra == 'lint'
Requires-Dist: mypy ; extra == 'lint'
Provides-Extra: test
Requires-Dist: pretend ; extra == 'test'
Requires-Dist: pytest ; extra == 'test'
Requires-Dist: pytest-cov ; extra == 'test'
